Metadata-Version: 2.4
Name: eth_portfolio_temp
Version: 0.3.3
Summary: eth-portfolio makes it easy to analyze your portfolio.
Home-page: https://github.com/BobTheBuidler/eth-portfolio
Author: BobTheBuidler
Author-email: bobthebuidlerdefi@gmail.com
Requires-Python: >=3.10,<3.14
Requires-Dist: checksum_dict>=2.1.7
Requires-Dist: dank_mids>=4.20.154
Requires-Dist: eth-brownie<1.23,>=1.22.0.dev0
Requires-Dist: eth_retry<1,>=0.3.4
Requires-Dist: evmspec>=0.4.1
Requires-Dist: ez-a-sync>=0.32.27
Requires-Dist: faster-async-lru==2.0.5
Requires-Dist: faster-eth-utils
Requires-Dist: numpy<3
Requires-Dist: pandas<3,>=1.4.3
Requires-Dist: typed-envs>=0.0.9
Requires-Dist: ypricemagic<5,>=4.10.6
Dynamic: author
Dynamic: author-email
Dynamic: home-page
Dynamic: requires-dist
Dynamic: requires-python
Dynamic: summary
